README.rst
SPF2IP.py
setup.cfg
setup.py
SPF2IP.egg-info/PKG-INFO
SPF2IP.egg-info/SOURCES.txt
SPF2IP.egg-info/dependency_links.txt
SPF2IP.egg-info/entry_points.txt
SPF2IP.egg-info/requires.txt
SPF2IP.egg-info/top_level.txt