Metadata-Version: 1.1
Name: SPF2IP
Version: 1.0.5
Summary: Python module to get IP addresses from an SPF record
Home-page: https://github.com/nathandines/SPF2IP
Author: Nathan Dines
Author-email: contact@ndines.com
License: MIT
Keywords: email spf ip development firewall
Platform: UNKNOWN
Classifier: Development Status :: 5 - Production/Stable
Classifier: Intended Audience :: Developers
Classifier: Topic :: Software Development :: Libraries :: Python Modules
Classifier: License :: OSI Approved :: MIT License
Classifier: Programming Language :: Python :: 2
Classifier: Programming Language :: Python :: 2.6
Classifier: Programming Language :: Python :: 2.7
Classifier: Programming Language :: Python :: 3
Classifier: Programming Language :: Python :: 3.3
Classifier: Programming Language :: Python :: 3.4
Classifier: Programming Language :: Python :: 3.5
Classifier: Programming Language :: Python :: 3.6
